{
  "$schema": "https://typedoc.org/schema.json",
  "entryPoints": ["index.ts"],
  "out": "docs",
  "name": "crnt",
  "theme": "default",
  "hideGenerator": true,
  "includeVersion": true,
  "searchInComments": true,
  "categorizeByGroup": false,
  "sort": ["kind", "instance-first", "alphabetical-ignoring-documents"],
  "readme": "README.md",
  "projectDocuments": ["README.md"],
  "alwaysCreateEntryPointModule": false,
  "exclude": ["**/*.test.ts", "node_modules/*", "docs/*", "dist/*"],
  "excludeExternals": true,
  "excludePrivate": true,
  "excludeProtected": true,
  "validation": {
    "notExported": true,
    "invalidLink": true,
    "notDocumented": false
  },
  "navigation": {
    "includeCategories": true,
    "includeGroups": true
  },
  "tsconfig": "tsconfig.json"
}
